{
    "prepare_queue": {
        "installed": [],
        "uninstalled": []
    },
    "config_munge": {
        "files": {}
    },
    "installed_plugins": {
        "cordova-plugin-file": {
            "PACKAGE_NAME": "com.ionicframework.confernece414740"
        },
        "cordova-sqlite-storage": {
            "PACKAGE_NAME": "com.ionicframework.confernece414740"
        },
        "cordova-plugin-whitelist": {
            "PACKAGE_NAME": "com.ionicframework.confernece414740"
        },
        "cordova-plugin-sms": {
            "PACKAGE_NAME": "com.ionicframework.confernece414740"
        },
        "cordova-plugin-android-permissions": {
            "PACKAGE_NAME": "com.ionicframework.confernece414740"
        },
        "cordova-plugin-device": {
            "PACKAGE_NAME": "com.ionicframework.confernece414740"
        },
        "cordova-plugin-console": {
            "PACKAGE_NAME": "com.ionicframework.confernece414740"
        },
        "cordova-plugin-splashscreen": {
            "PACKAGE_NAME": "com.ionicframework.confernece414740"
        },
        "cordova-plugin-statusbar": {
            "PACKAGE_NAME": "com.ionicframework.confernece414740"
        },
        "ionic-plugin-keyboard": {
            "PACKAGE_NAME": "com.ionicframework.confernece414740"
        }
    },
    "dependent_plugins": {
        "cordova-plugin-compat": {
            "PACKAGE_NAME": "com.ionicframework.confernece414740"
        }
    }
}